robotlibcore.py
robotframework_pythonlibcore-4.1.1.dist-info/LICENSE.txt
robotframework_pythonlibcore-4.1.1.dist-info/METADATA
robotframework_pythonlibcore-4.1.1.dist-info/WHEEL
robotframework_pythonlibcore-4.1.1.dist-info/top_level.txt
robotframework_pythonlibcore-4.1.1.dist-info/RECORD
