Metadata-Version: 2.1
Name: robotframework-pythonlibcore
Version: 4.1.1
Summary: Tools to ease creating larger test libraries for Robot Framework using Python.
Home-page: https://github.com/robotframework/PythonLibCore
Author: Tatu Aalto
Author-email: aalto.tatu@gmail.com
License: Apache License 2.0
Keywords: robotframework testing testautomation library development
Platform: any
Classifier: Development Status :: 5 - Production/Stable
Classifier: License :: OSI Approved :: Apache Software License
Classifier: Operating System :: OS Independent
Classifier: Programming Language :: Python :: 3
Classifier: Programming Language :: Python :: 3.7
Classifier: Programming Language :: Python :: 3.8
Classifier: Programming Language :: Python :: 3.9
Classifier: Programming Language :: Python :: 3.10
Classifier: Programming Language :: Python :: 3 :: Only
Classifier: Programming Language :: Python :: Implementation :: CPython
Classifier: Programming Language :: Python :: Implementation :: PyPy
Classifier: Topic :: Software Development :: Testing
Classifier: Framework :: Robot Framework
Requires-Python: >=3.7, <4
License-File: LICENSE.txt
